pystack.py
pstack-0.7.1.dist-info/DESCRIPTION.rst
pstack-0.7.1.dist-info/METADATA
pstack-0.7.1.dist-info/RECORD
pstack-0.7.1.dist-info/WHEEL
pstack-0.7.1.dist-info/entry_points.txt
pstack-0.7.1.dist-info/metadata.json
pstack-0.7.1.dist-info/top_level.txt
